mkdocs_ezglossary_plugin/__init__.py
mkdocs_ezglossary_plugin/glossary.py
mkdocs_ezglossary_plugin/plugin.py
mkdocs_ezglossary_plugin/plurals.py
mkdocs_ezglossary_plugin/template.py
mkdocs_ezglossary_plugin/templates/definition.html
mkdocs_ezglossary_plugin/templates/link.html
mkdocs_ezglossary_plugin/templates/refs-list.html
mkdocs_ezglossary_plugin/templates/refs-short.html
mkdocs_ezglossary_plugin/templates/summary-detailed.html
mkdocs_ezglossary_plugin/templates/summary-table.html
mkdocs_ezglossary_plugin/templates/summary.html
mkdocs_ezglossary_plugin-1.7.0.dist-info/LICENSE
mkdocs_ezglossary_plugin-1.7.0.dist-info/METADATA
mkdocs_ezglossary_plugin-1.7.0.dist-info/WHEEL
mkdocs_ezglossary_plugin-1.7.0.dist-info/entry_points.txt
mkdocs_ezglossary_plugin-1.7.0.dist-info/top_level.txt
mkdocs_ezglossary_plugin-1.7.0.dist-info/RECORD
