Metadata-Version: 2.1
Name: mkdocs-ezglossary-plugin
Version: 1.7.0
Summary: manage multiple glossaries in mkdocs
Project-URL: Homepage, https://github.com/realtimeprojects/mkdocs-ezglossary
Project-URL: Bug Tracker, https://github.com/realtimeprojects/mkdocs-ezglossary/issues
Project-URL: Documentation, https://realtimeprojects.github.io/mkdocs-ezglossary
Keywords: mkdocs,glossary,plugin,references,links
License-File: LICENSE
Requires-Dist: mkdocs>=1.1.0
Requires-Dist: jinja2
Requires-Dist: inflect
